naters_utils/__init__.py
naters_utils/_hello.py
naters_utils/functions.py
naters_utils/iterables.py
naters_utils/objects.py
naters_utils-0.3.0.dist-info/LICENSE.txt
naters_utils-0.3.0.dist-info/METADATA
naters_utils-0.3.0.dist-info/WHEEL
naters_utils-0.3.0.dist-info/top_level.txt
naters_utils-0.3.0.dist-info/RECORD
