Metadata-Version: 2.1
Name: naters-utils
Version: 0.3.0
Author-email: Nater0214 <gamer@nater0214.com>
License: GNU GENERAL PUBLIC LICENSE
Requires-Python: >=3.7
License-File: LICENSE.txt
Provides-Extra: dev
Requires-Dist: pytest ; extra == 'dev'
